LICENSE
MANIFEST.in
README.md
requirements.txt
setup.py
blimp/__init__.py
blimp.egg-info/PKG-INFO
blimp.egg-info/SOURCES.txt
blimp.egg-info/dependency_links.txt
blimp.egg-info/requires.txt
blimp.egg-info/top_level.txt
tests/__init__.py
tests/test_blimp.py