Metadata-Version: 1.1
Name: blimp
Version: 0.0.2
Summary: Blimp library for Python
Home-page: https://github.com/getblimp/blimp-python/
Author: Jose Padilla
Author-email: jpadilla@getblimp.com
License: MIT License
Download-URL: https://github.com/GetBlimp/blimp-python/tarball/master
Platform: UNKNOWN
